{
    "name": "Global Information",
    "numberOfRequests": {
        "total": 14,
        "ok": 13,
        "ko": 1
    },
    "minResponseTime": {
        "total": 82,
        "ok": 82,
        "ko": 1338
    },
    "maxResponseTime": {
        "total": 6458,
        "ok": 6458,
        "ko": 1338
    },
    "meanResponseTime": {
        "total": 1136,
        "ok": 1121,
        "ko": 1338
    },
    "standardDeviation": {
        "total": 1629,
        "ok": 1690,
        "ko": 0
    },
    "percentiles1": {
        "total": 515,
        "ok": 514,
        "ko": 1338
    },
    "percentiles2": {
        "total": 1210,
        "ok": 824,
        "ko": 1338
    },
    "percentiles3": {
        "total": 3821,
        "ok": 4024,
        "ko": 1338
    },
    "percentiles4": {
        "total": 5931,
        "ok": 5971,
        "ko": 1338
    },
    "group1": {
        "name": "t < 800 ms",
        "count": 9,
        "percentage": 64
    },
    "group2": {
        "name": "800 ms < t < 1200 ms",
        "count": 1,
        "percentage": 7
    },
    "group3": {
        "name": "t > 1200 ms",
        "count": 3,
        "percentage": 21
    },
    "group4": {
        "name": "failed",
        "count": 1,
        "percentage": 7
    },
    "meanNumberOfRequestsPerSecond": {
        "total": 0.1794871794871795,
        "ok": 0.16666666666666666,
        "ko": 0.01282051282051282
    }
}